sqlicrawler/__init__.py
sqlicrawler/blacklist.txt
sqlicrawler/log.py
sqlicrawler/meta.py
sqlicrawler/types.py
sqlicrawler/utils.py
sqlicrawler-0.1.3.dist-info/entry_points.txt
sqlicrawler-0.1.3.dist-info/WHEEL
sqlicrawler-0.1.3.dist-info/METADATA
sqlicrawler-0.1.3.dist-info/RECORD
