Metadata-Version: 2.1
Name: sqlicrawler
Version: 0.1.3
Summary: SQLi Crawler with JavaScript support.
Author: Sergey M
Author-email: tz4678@gmail.com
Requires-Python: >=3.8,<4.0
Classifier: Programming Language :: Python :: 3
Classifier: Programming Language :: Python :: 3.8
Classifier: Topic :: Internet
Classifier: Topic :: Security
Classifier: Topic :: Software Development :: Libraries :: Python Modules
Classifier: Topic :: Utilities
Requires-Dist: aiodns (>=2.0.0,<3.0.0)
Requires-Dist: aiohttp (>=3.6.2,<4.0.0)
Requires-Dist: aiohttp_socks (>=0.5.3,<0.6.0)
Requires-Dist: click (>=7.1.2,<8.0.0)
Requires-Dist: pyppeteer (>=0.2.2,<0.3.0)
Requires-Dist: ujson (>=3.1.0,<4.0.0)
